servclake/__init__.py
servclake/config.py
servclake/delta/__init__.py
servclake/parquet/__init__.py
servc_lake-1.2.1.dist-info/LICENSE
servc_lake-1.2.1.dist-info/METADATA
servc_lake-1.2.1.dist-info/WHEEL
servc_lake-1.2.1.dist-info/top_level.txt
servc_lake-1.2.1.dist-info/RECORD
