Metadata-Version: 2.1
Name: servc-lake
Version: 1.2.1
Summary: Server implmentation of services for python
Author-email: Yusuf Ali <ali@yusuf.email>
Project-URL: Homepage, https://github.com/serv-c/servc-lake
Project-URL: Bug Tracker, https://github.com/serv-c/servc-lake/issues
Classifier: Programming Language :: Python :: 3
Classifier: License :: OSI Approved :: MIT License
Classifier: Operating System :: OS Independent
Requires-Python: >=3.11
License-File: LICENSE
